{
    "planeta": "{\"id\":\"Planeta: Rochoso (0)\",\"tipo\":\"Rochoso\",\"biomas\":[\"{\\\"id\\\":\\\"Planeta: Rochoso (0) - Bioma: Planície (0)\\\",\\\"tipo\\\":\\\"Planície\\\",\\\"recursos\\\":[]}\",\"{\\\"id\\\":\\\"Planeta: Rochoso (0) - Bioma: Planície (1)\\\",\\\"tipo\\\":\\\"Planície\\\",\\\"recursos\\\":[]}\",\"{\\\"id\\\":\\\"Planeta: Rochoso (0) - Bioma: Planície (2)\\\",\\\"tipo\\\":\\\"Planície\\\",\\\"recursos\\\":[{\\\"id\\\":\\\"12\\\",\\\"nome\\\":\\\"Cristal de Quartzo\\\",\\\"raridade\\\":0,\\\"tamanho\\\":1}]}\",\"{\\\"id\\\":\\\"Planeta: Rochoso (0) - Bioma: Deserto (3)\\\",\\\"tipo\\\":\\\"Deserto\\\",\\\"recursos\\\":[{\\\"id\\\":\\\"2\\\",\\\"nome\\\":\\\"Minério de Cobre\\\",\\\"raridade\\\":0,\\\"tamanho\\\":1}]}\",\"{\\\"id\\\":\\\"Planeta: Rochoso (0) - Bioma: Deserto (4)\\\",\\\"tipo\\\":\\\"Deserto\\\",\\\"recursos\\\":[{\\\"id\\\":\\\"6\\\",\\\"nome\\\":\\\"Gás Oxigênio\\\",\\\"raridade\\\":1,\\\"tamanho\\\":1},{\\\"id\\\":\\\"1\\\",\\\"nome\\\":\\\"Minério de Ferro\\\",\\\"raridade\\\":0,\\\"tamanho\\\":1},{\\\"id\\\":\\\"4\\\",\\\"nome\\\":\\\"Nióbio\\\",\\\"raridade\\\":3,\\\"tamanho\\\":2},{\\\"id\\\":\\\"3\\\",\\\"nome\\\":\\\"Titânio\\\",\\\"raridade\\\":1,\\\"tamanho\\\":2},{\\\"id\\\":\\\"12\\\",\\\"nome\\\":\\\"Cristal de Quartzo\\\",\\\"raridade\\\":0,\\\"tamanho\\\":1}]}\"]}",
    "jogador": {
        "nome": "gameMaster",
        "vida": 100,
        "vidaMaxima": 100,
        "escudo": 50,
        "escudoMaximo": 50,
        "historico": [
            "Planeta: Rochoso (0) - Bioma: Planície (0)",
            "Planeta: Rochoso (0) - Bioma: Planície (1)",
            "Planeta: Rochoso (0) - Bioma: Planície (2)"
        ],
        "inventario": {
            "capacidadeMaxima": 100,
            "capacidadeAtual": 6,
            "slots": [
                [
                    {
                        "id": "12",
                        "nome": "Cristal de Quartzo",
                        "raridade": 0,
                        "tamanho": 1
                    },
                    6
                ]
            ]
        },
        "moedas": 100
    }
}